README.txt
setup.cfg
setup.py
collective/__init__.py
collective.types.citation.egg-info/PKG-INFO
collective.types.citation.egg-info/SOURCES.txt
collective.types.citation.egg-info/dependency_links.txt
collective.types.citation.egg-info/entry_points.txt
collective.types.citation.egg-info/namespace_packages.txt
collective.types.citation.egg-info/not-zip-safe
collective.types.citation.egg-info/requires.txt
collective.types.citation.egg-info/top_level.txt
collective/types/__init__.py
collective/types/citation/__init__.py
collective/types/citation/config.py
collective/types/citation/content.py
collective/types/citation/setuphandlers.py
collective/types/citation/browser/__init__.py
collective/types/citation/browser/citation.py
collective/types/citation/browser/collage.py
collective/types/citation/browser/page_wrapper.py
collective/types/citation/browser/util.py
collective/types/citation/tests/__init__.py
collective/types/citation/tests/base.py
collective/types/citation/tests/test_citation.py
collective/types/citation/tests/test_doctests.py
collective/types/citation/tests/test_setup.py