Metadata-Version: 1.0
Name: collective.types.citation
Version: 9.06
Summary: Citation content type
Home-page: http://cphi.washington.edu
Author: Liz Dahlstrom
Author-email: lhill2@u.washington.edu
License: GPL 2
Keywords: plone types citation
Platform: UNKNOWN
Classifier: Development Status :: 4 - Beta
Classifier: Framework :: Plone
Classifier: Framework :: Zope2
Classifier: Framework :: Zope3
Classifier: Programming Language :: Python
Classifier: Topic :: Software Development :: Libraries :: Python Modules
